hoox/__init__.py
hoox/hoox.py
hoox/resources/__init__.py
hoox/resources/hook-runner.sh
hoox/resources/hoox.py
hoox-0.0.5.data/data/README.md
hoox-0.0.5.data/data/hoox.version
hoox-0.0.5.dist-info/METADATA
hoox-0.0.5.dist-info/RECORD
hoox-0.0.5.dist-info/WHEEL
hoox-0.0.5.dist-info/entry_points.txt
hoox-0.0.5.dist-info/top_level.txt
