Metadata-Version: 2.1
Name: hoox
Version: 0.0.5
Summary: Git hooks manager
Home-page: https://github.com/kirillsulim/hoox
Author: Kirill Sulim
Author-email: kirillsulim@gmail.com
License: UNKNOWN
Platform: UNKNOWN
Classifier: Environment :: Console
Classifier: Intended Audience :: Developers
Classifier: Programming Language :: Python :: 3
Classifier: Programming Language :: Python :: 3.6
Classifier: License :: OSI Approved :: MIT License
Classifier: Operating System :: OS Independent
